agentic/__init__.py
agentic/browser.py
agentic/cli.py
agentic/config.py
agentic/mcp.py
agentic/rag.py
agentic/tools.py
agentic_cli_coder-1.2.1.dist-info/licenses/LICENSE
tests/__init__.py
tests/test_cli.py
tests/test_config.py
tests/test_tools.py
agentic_cli_coder-1.2.1.dist-info/METADATA
agentic_cli_coder-1.2.1.dist-info/WHEEL
agentic_cli_coder-1.2.1.dist-info/entry_points.txt
agentic_cli_coder-1.2.1.dist-info/top_level.txt
agentic_cli_coder-1.2.1.dist-info/RECORD
