Metadata-Version: 2.4
Name: agentic-cli-coder
Version: 1.2.1
Summary: Open source, cheap, and premier coding agent
Author: 
License: ISC
License-File: LICENSE
Requires-Dist: chromadb
Requires-Dist: cryptography
Requires-Dist: litellm
Requires-Dist: pathspec
Requires-Dist: playwright
Requires-Dist: prompt-toolkit>=3.0
Requires-Dist: python-dotenv
Requires-Dist: requests
Requires-Dist: rich
Requires-Dist: simple-term-menu
Requires-Dist: tiktoken
Provides-Extra: test
Requires-Dist: pytest; extra == "test"
Requires-Dist: pytest-mock; extra == "test"
Dynamic: description
Dynamic: description-content-type
Dynamic: license
Dynamic: license-file
Dynamic: provides-extra
Dynamic: requires-dist
Dynamic: summary
